setup.cfg
setup.py
Flask_SQLAlchemy_Cache.egg-info/PKG-INFO
Flask_SQLAlchemy_Cache.egg-info/SOURCES.txt
Flask_SQLAlchemy_Cache.egg-info/dependency_links.txt
Flask_SQLAlchemy_Cache.egg-info/requires.txt
Flask_SQLAlchemy_Cache.egg-info/top_level.txt
flask_sqlalchemy_cache/__init__.py
flask_sqlalchemy_cache/core.py