Metadata-Version: 1.1
Name: Flask-SQLAlchemy-Cache
Version: 0.1.2
Summary: CachingQuery implementation to Flask using Flask-SQLAlchemy and Flask-Cache
Home-page: http://www.github.com/iurisilvio/Flask-SQLAlchemy-Cache
Author: Iuri de Silvio
Author-email: iurisilvio@gmail.com
License: MIT
Platform: any
Classifier: Environment :: Web Environment
Classifier: Intended Audience :: Developers
Classifier: License :: OSI Approved :: MIT License
Classifier: Operating System :: OS Independent
Classifier: Programming Language :: Python
Classifier: Programming Language :: Python :: 3
Classifier: Topic :: Internet :: WWW/HTTP :: Dynamic Content
Classifier: Topic :: Software Development :: Libraries :: Python Modules
